YennMedlib/__init__.py
YennMedlib/fileSaviour.py
YennMedlib/myFunction.py
YennMedlib-0.1.0.dist-info/LICENSE
YennMedlib-0.1.0.dist-info/METADATA
YennMedlib-0.1.0.dist-info/WHEEL
YennMedlib-0.1.0.dist-info/top_level.txt
YennMedlib-0.1.0.dist-info/RECORD
